<?xml version="1.0" encoding="utf-8"?>
<!DOCTYPE hibernate-mapping PUBLIC "-//Hibernate/Hibernate Mapping DTD 3.0//EN"
"http://hibernate.sourceforge.net/hibernate-mapping-3.0.dtd">
<!-- 
	Mapping file autogenerated by MyEclipse Persistence Tools
-->
<hibernate-mapping>
	<class name="bbr.b2b.falabella.logistic.buyorders.entities.OrderConsolidated" table="ORDER_CONSOLIDATED"
		entity-name="bbr.b2b.falabella.logistic.buyorders.entities.OrderConsolidated" schema="LOGISTICA" > 
		<id name="id" type="java.lang.Long">
			<column name="ID" />
			<generator class="identity">
				<param name="sequence">ORDER_CONSOLIDATED_SEQUENCE</param>
				<param name="parameters">AS BIGINT CACHE 100</param>
			</generator>
		</id>

		<property name="ticket" type="java.lang.Long" not-null="true"></property>
		
		<many-to-one name="order"
			class="bbr.b2b.falabella.logistic.buyorders.entities.Order" column="ORDER_ID"
			not-null="true" />	
	</class>
</hibernate-mapping>
