<?xml version="1.0" encoding="utf-8"?>
<!DOCTYPE hibernate-mapping PUBLIC "-//Hibernate/Hibernate Mapping DTD 3.0//EN"
"http://hibernate.sourceforge.net/hibernate-mapping-3.0.dtd">
<!-- 
	Mapping file autogenerated by MyEclipse Persistence Tools
-->
<hibernate-mapping>
	<class name="bbr.b2b.logistic.buyorders.entities.Retailer" table="RETAILER" entity-name="bbr.b2b.logistic.buyorders.entities.Retailer" schema="LOGISTICA">
		<id name="id" type="java.lang.Long">
			<column name="ID" />
			<generator class="identity">
				<param name="sequence">RETAILER_SEQUENCE</param>
				<param name="parameters">AS BIGINT CACHE 100</param>
			</generator>
		</id>
		
		<property name="code" type="java.lang.String" column="CODE" length="250" unique="true" not-null="true"/>
		<property name="dni" type="java.lang.String" column="DNI" length="250"/>
		<property name="description" type="java.lang.String" column="DESCRIPTION" length="250"/>
		<property name="gln" type="java.lang.String" column="GLN" length="250"/>

	</class>
</hibernate-mapping>
